se_wrapper/__init__.py
se_wrapper/browser_driver.py
se_wrapper/errors.py
se_wrapper/help_utils.py
se_wrapper/waits.py
se_wrapper/element/__init__.py
se_wrapper/element/element_waits.py
se_wrapper/element/expectations.py
se_wrapper/element/se_element_interface.py
se_wrapper/element/se_elements_array.py
se_wrapper/element/se_web_element.py
selen_kaa-0.0.1.dist-info/LICENSE
selen_kaa-0.0.1.dist-info/METADATA
selen_kaa-0.0.1.dist-info/WHEEL
selen_kaa-0.0.1.dist-info/top_level.txt
selen_kaa-0.0.1.dist-info/RECORD
